[
    {
        "no":"1",
        "title":"Front-End Engineer",
        "paragraphs":[
            "Donec suscipit sem ac arcu dapibus, vel tristique eros fringilla.",
            "Nulla facilisis est sollicitudin sapien consectetur, et sollicitudin lacus venenatis.",
            "Phasellus sit amet erat sodales, varius neque nec, tincidunt mauris.",
            "Maecenas eu elit porta, tempor nibh a, euismod quam.",
            "Aenean sed leo ac quam dignissim condimentum.",
            "Fusce mattis ligula id dui aliquet bibendum."
        ]
    },
    {
        "no":"2",
        "title":"Back-End Engineer",
        "paragraphs":[
            "Phasellus sit amet erat sodales, varius neque nec, tincidunt mauris.",
            "Maecenas eu elit porta, tempor nibh a, euismod quam.",
            "Phasellus quis nulla hendrerit, hendrerit mauris eu, ultrices turpis.",
            "Aenean ultricies sem in dolor tristique, ut imperdiet ligula tristique."
        ]
    },
    {
        "no":"3",
        "title":"Android Developer",
        "paragraphs":[
            "Mauris nec ante quis odio fermentum vehicula ac et metus.",
            "Integer ac turpis vel velit tempor varius faucibus a magna.",
            "Cras in leo vulputate nisl maximus placerat.",
            "Proin maximus sem eget auctor tempor.",
            "Phasellus quis nulla hendrerit, hendrerit mauris eu, ultrices turpis.",
            "Aenean ultricies sem in dolor tristique, ut imperdiet ligula tristique.",
            "Donec semper ligula nec lobortis pellentesque."
        ]
    },
    {
        "no":"4",
        "title":"IOS Developer",
        "paragraphs":[
            "Cras in leo vulputate nisl maximus placerat.",
            "Mauris nec ante quis odio fermentum vehicula ac et metus.",
            "Maecenas eu elit porta, tempor nibh a, euismod quam.",
            "Phasellus quis nulla hendrerit, hendrerit mauris eu, ultrices turpis."
        ]
    },
    {
        "no":"5",
        "title":"UI/UX Designer",
        "paragraphs":[
            "Aenean ultricies sem in dolor tristique, ut imperdiet ligula tristique.",
            "Donec semper ligula nec lobortis pellentesque.",
            "Maecenas eu elit porta, tempor nibh a, euismod quam.",
            "Phasellus quis nulla hendrerit, hendrerit mauris eu, ultrices turpis."
        ]
    }
]